pygenetic/ANNEvolve.py
pygenetic/ChromosomeFactory.py
pygenetic/Evolution.py
pygenetic/GAEngine.py
pygenetic/Population.py
pygenetic/SimpleGA.py
pygenetic/Statistics.py
pygenetic/Utils.py
pygenetic-1.0.2.dist-info/LICENSE
pygenetic-1.0.2.dist-info/METADATA
pygenetic-1.0.2.dist-info/WHEEL
pygenetic-1.0.2.dist-info/top_level.txt
pygenetic-1.0.2.dist-info/RECORD
