Metadata-Version: 2.1
Name: pygenetic
Version: 1.0.2
Summary: An Efficient Python Genetic Algorithm API
Home-page: https://github.com/danny311296/pygenetic
Author: Bharatraj S Telkar, Daniel Isaac, Shreyas V Patil
Author-email: telkarraj@gmail.com, danielbcbs2@gmail.com, pshreyasv100@gmail.com
License: MIT
Platform: UNKNOWN
Classifier: Programming Language :: Python :: 3
Classifier: License :: OSI Approved :: MIT License
Classifier: Operating System :: OS Independent
Requires-Dist: rstr (==2.2.6)
Requires-Dist: numpy (==1.15.4)
Requires-Dist: matplotlib (==2.2.2)
